{
	"archive" : {},
	"artifacts" : 
	[
		{
			"path" : "libfeature_trackers.a"
		}
	],
	"backtrace" : 1,
	"backtraceGraph" : 
	{
		"commands" : 
		[
			"add_library",
			"_install",
			"ament_cmake_symlink_install_targets",
			"install",
			"add_compile_options",
			"include_directories",
			"target_include_directories"
		],
		"files" : 
		[
			"CMakeLists.txt",
			"/opt/ros/jazzy/share/ament_cmake_core/cmake/symlink_install/ament_cmake_symlink_install_targets.cmake",
			"/opt/ros/jazzy/share/ament_cmake_core/cmake/symlink_install/install.cmake"
		],
		"nodes" : 
		[
			{
				"file" : 0
			},
			{
				"command" : 0,
				"file" : 0,
				"line" : 20,
				"parent" : 0
			},
			{
				"command" : 3,
				"file" : 0,
				"line" : 57,
				"parent" : 0
			},
			{
				"command" : 2,
				"file" : 2,
				"line" : 37,
				"parent" : 2
			},
			{
				"command" : 1,
				"file" : 1,
				"line" : 50,
				"parent" : 3
			},
			{
				"command" : 4,
				"file" : 0,
				"line" : 4,
				"parent" : 0
			},
			{
				"command" : 5,
				"file" : 0,
				"line" : 14,
				"parent" : 0
			},
			{
				"command" : 6,
				"file" : 0,
				"line" : 29,
				"parent" : 0
			}
		]
	},
	"compileGroups" : 
	[
		{
			"compileCommandFragments" : 
			[
				{
					"backtrace" : 5,
					"fragment" : "-std=c++17"
				}
			],
			"includes" : 
			[
				{
					"backtrace" : 6,
					"path" : "/opt/ros/jazzy/include/sensor_msgs"
				},
				{
					"backtrace" : 6,
					"path" : "/opt/ros/jazzy/include/rclcpp"
				},
				{
					"backtrace" : 7,
					"path" : "/home/soumith/vnav/TEAM_7/lab3/include"
				},
				{
					"backtrace" : 6,
					"isSystem" : true,
					"path" : "/usr/include/opencv4"
				}
			],
			"language" : "CXX",
			"sourceIndexes" : 
			[
				0,
				1,
				2,
				3,
				4,
				5
			]
		}
	],
	"id" : "feature_trackers::@6890427a1f51a3e7e1df",
	"install" : 
	{
		"destinations" : 
		[
			{
				"backtrace" : 4,
				"path" : "lib"
			}
		],
		"prefix" : 
		{
			"path" : "/home/soumith/vnav/TEAM_7/lab3/install/lab_3"
		}
	},
	"name" : "feature_trackers",
	"nameOnDisk" : "libfeature_trackers.a",
	"paths" : 
	{
		"build" : ".",
		"source" : "."
	},
	"sourceGroups" : 
	[
		{
			"name" : "Source Files",
			"sourceIndexes" : 
			[
				0,
				1,
				2,
				3,
				4,
				5
			]
		}
	],
	"sources" : 
	[
		{
			"backtrace" : 1,
			"compileGroupIndex" : 0,
			"path" : "src/feature_tracker.cpp",
			"sourceGroupIndex" : 0
		},
		{
			"backtrace" : 1,
			"compileGroupIndex" : 0,
			"path" : "src/sift_feature_tracker.cpp",
			"sourceGroupIndex" : 0
		},
		{
			"backtrace" : 1,
			"compileGroupIndex" : 0,
			"path" : "src/akaze_feature_tracker.cpp",
			"sourceGroupIndex" : 0
		},
		{
			"backtrace" : 1,
			"compileGroupIndex" : 0,
			"path" : "src/orb_feature_tracker.cpp",
			"sourceGroupIndex" : 0
		},
		{
			"backtrace" : 1,
			"compileGroupIndex" : 0,
			"path" : "src/brisk_feature_tracker.cpp",
			"sourceGroupIndex" : 0
		},
		{
			"backtrace" : 1,
			"compileGroupIndex" : 0,
			"path" : "src/lk_feature_tracker.cpp",
			"sourceGroupIndex" : 0
		}
	],
	"type" : "STATIC_LIBRARY"
}
